{
  "model_id": "Tencent-Hunyuan/HunyuanDiT-v1.2-Diffusers",
  "task": "text-to-image",
  "nickname": "Hunyuan-DiT 1.2",
  "total_params_billions": 1.5,
  "activated_params_billions": 1.5,
  "weight_precision": "bfloat16",
  "configurations": [
    {
      "gpu_model": "H100",
      "num_gpus": 2,
      "batch_size": 1,
      "parallelization": {
        "ulysses_degree": 1,
        "ring_degree": 2
      },
      "batch_latency_s": 6.656707286834717,
      "avg_power_watts": 837.7622764105226,
      "inference_steps": 50,
      "energy_per_image_joules": 5576.738250017166,
      "throughput_images_per_sec": 0.15022442131078034,
      "image_height": 1024,
      "image_width": 1024
    },
    {
      "gpu_model": "H100",
      "num_gpus": 4,
      "batch_size": 1,
      "parallelization": {
        "ulysses_degree": 1,
        "ring_degree": 4
      },
      "batch_latency_s": 5.9487228989601135,
      "avg_power_watts": 1295.943411880247,
      "inference_steps": 50,
      "energy_per_image_joules": 7709.2082500085235,
      "throughput_images_per_sec": 0.16810330838822704,
      "image_height": 1024,
      "image_width": 1024
    },
    {
      "gpu_model": "H100",
      "num_gpus": 8,
      "batch_size": 1,
      "parallelization": {
        "ulysses_degree": 1,
        "ring_degree": 8
      },
      "batch_latency_s": 7.33108115196228,
      "avg_power_watts": 1848.4441406561116,
      "inference_steps": 50,
      "energy_per_image_joules": 13551.094000019133,
      "throughput_images_per_sec": 0.13640552863506825,
      "image_height": 1024,
      "image_width": 1024
    },
    {
      "gpu_model": "H100",
      "num_gpus": 2,
      "batch_size": 1,
      "parallelization": {
        "ulysses_degree": 2,
        "ring_degree": 1
      },
      "batch_latency_s": 6.602875471115112,
      "avg_power_watts": 837.6523643784154,
      "inference_steps": 50,
      "energy_per_image_joules": 5530.914250075817,
      "throughput_images_per_sec": 0.15144916852886173,
      "image_height": 1024,
      "image_width": 1024
    },
    {
      "gpu_model": "H100",
      "num_gpus": 4,
      "batch_size": 1,
      "parallelization": {
        "ulysses_degree": 2,
        "ring_degree": 2
      },
      "batch_latency_s": 5.501688539981842,
      "avg_power_watts": 1332.7222991096812,
      "inference_steps": 50,
      "energy_per_image_joules": 7332.222999989986,
      "throughput_images_per_sec": 0.18176237944638365,
      "image_height": 1024,
      "image_width": 1024
    },
    {
      "gpu_model": "H100",
      "num_gpus": 8,
      "batch_size": 1,
      "parallelization": {
        "ulysses_degree": 2,
        "ring_degree": 4
      },
      "batch_latency_s": 6.288421094417572,
      "avg_power_watts": 1910.7270043797855,
      "inference_steps": 50,
      "energy_per_image_joules": 12015.45600001514,
      "throughput_images_per_sec": 0.1590224294756169,
      "image_height": 1024,
      "image_width": 1024
    },
    {
      "gpu_model": "H100",
      "num_gpus": 4,
      "batch_size": 1,
      "parallelization": {
        "ulysses_degree": 4,
        "ring_degree": 1
      },
      "batch_latency_s": 4.92831552028656,
      "avg_power_watts": 1375.0278816589503,
      "inference_steps": 50,
      "energy_per_image_joules": 6776.5712500065565,
      "throughput_images_per_sec": 0.20290908645837966,
      "image_height": 1024,
      "image_width": 1024
    },
    {
      "gpu_model": "H100",
      "num_gpus": 8,
      "batch_size": 1,
      "parallelization": {
        "ulysses_degree": 4,
        "ring_degree": 2
      },
      "batch_latency_s": 5.508120238780975,
      "avg_power_watts": 1954.866185423773,
      "inference_steps": 50,
      "energy_per_image_joules": 10767.638000041246,
      "throughput_images_per_sec": 0.18155013991149077,
      "image_height": 1024,
      "image_width": 1024
    },
    {
      "gpu_model": "H100",
      "num_gpus": 8,
      "batch_size": 1,
      "parallelization": {
        "ulysses_degree": 8,
        "ring_degree": 1
      },
      "batch_latency_s": 4.7598941922187805,
      "avg_power_watts": 2069.6099224429913,
      "inference_steps": 50,
      "energy_per_image_joules": 9851.124249994755,
      "throughput_images_per_sec": 0.210088703575543,
      "image_height": 1024,
      "image_width": 1024
    },
    {
      "gpu_model": "H100",
      "num_gpus": 2,
      "batch_size": 16,
      "parallelization": {
        "ulysses_degree": 1,
        "ring_degree": 2
      },
      "batch_latency_s": 76.95695453882217,
      "avg_power_watts": 1141.5383479825562,
      "inference_steps": 50,
      "energy_per_image_joules": 5490.5821718759835,
      "throughput_images_per_sec": 0.20790843525296396,
      "image_height": 1024,
      "image_width": 1024
    },
    {
      "gpu_model": "H100",
      "num_gpus": 4,
      "batch_size": 16,
      "parallelization": {
        "ulysses_degree": 1,
        "ring_degree": 4
      },
      "batch_latency_s": 43.75231176614761,
      "avg_power_watts": 2410.341499522674,
      "inference_steps": 50,
      "energy_per_image_joules": 6591.125796874985,
      "throughput_images_per_sec": 0.3656949622575063,
      "image_height": 1024,
      "image_width": 1024
    },
    {
      "gpu_model": "H100",
      "num_gpus": 8,
      "batch_size": 16,
      "parallelization": {
        "ulysses_degree": 1,
        "ring_degree": 8
      },
      "batch_latency_s": 36.876366794109344,
      "avg_power_watts": 3605.018099863573,
      "inference_steps": 50,
      "energy_per_image_joules": 8308.748109373264,
      "throughput_images_per_sec": 0.4338822229785351,
      "image_height": 1024,
      "image_width": 1024
    },
    {
      "gpu_model": "H100",
      "num_gpus": 2,
      "batch_size": 16,
      "parallelization": {
        "ulysses_degree": 2,
        "ring_degree": 1
      },
      "batch_latency_s": 77.77985298633575,
      "avg_power_watts": 1122.1693105443221,
      "inference_steps": 50,
      "energy_per_image_joules": 5455.135249994695,
      "throughput_images_per_sec": 0.20570879714584772,
      "image_height": 1024,
      "image_width": 1024
    },
    {
      "gpu_model": "H100",
      "num_gpus": 4,
      "batch_size": 16,
      "parallelization": {
        "ulysses_degree": 2,
        "ring_degree": 2
      },
      "batch_latency_s": 39.44449543952942,
      "avg_power_watts": 2525.8695830633874,
      "inference_steps": 50,
      "energy_per_image_joules": 6226.978203124367,
      "throughput_images_per_sec": 0.4056332784007563,
      "image_height": 1024,
      "image_width": 1024
    },
    {
      "gpu_model": "H100",
      "num_gpus": 8,
      "batch_size": 16,
      "parallelization": {
        "ulysses_degree": 2,
        "ring_degree": 4
      },
      "batch_latency_s": 24.74483150243759,
      "avg_power_watts": 4508.797048750522,
      "inference_steps": 50,
      "energy_per_image_joules": 6973.088953126222,
      "throughput_images_per_sec": 0.6465996747007089,
      "image_height": 1024,
      "image_width": 1024
    },
    {
      "gpu_model": "H100",
      "num_gpus": 4,
      "batch_size": 16,
      "parallelization": {
        "ulysses_degree": 4,
        "ring_degree": 1
      },
      "batch_latency_s": 38.25646585226059,
      "avg_power_watts": 2503.4179220805067,
      "inference_steps": 50,
      "energy_per_image_joules": 5985.74514062563,
      "throughput_images_per_sec": 0.41822995521303635,
      "image_height": 1024,
      "image_width": 1024
    },
    {
      "gpu_model": "H100",
      "num_gpus": 8,
      "batch_size": 16,
      "parallelization": {
        "ulysses_degree": 4,
        "ring_degree": 2
      },
      "batch_latency_s": 21.935042440891266,
      "avg_power_watts": 4748.841700704109,
      "inference_steps": 50,
      "energy_per_image_joules": 6510.377765626181,
      "throughput_images_per_sec": 0.7294264436969052,
      "image_height": 1024,
      "image_width": 1024
    },
    {
      "gpu_model": "H100",
      "num_gpus": 8,
      "batch_size": 16,
      "parallelization": {
        "ulysses_degree": 8,
        "ring_degree": 1
      },
      "batch_latency_s": 21.01629912853241,
      "avg_power_watts": 4790.3259814819685,
      "inference_steps": 50,
      "energy_per_image_joules": 6292.182734375354,
      "throughput_images_per_sec": 0.7613138689236623,
      "image_height": 1024,
      "image_width": 1024
    },
    {
      "gpu_model": "H100",
      "num_gpus": 2,
      "batch_size": 2,
      "parallelization": {
        "ulysses_degree": 1,
        "ring_degree": 2
      },
      "batch_latency_s": 11.504297137260437,
      "avg_power_watts": 972.585231984622,
      "inference_steps": 50,
      "energy_per_image_joules": 5594.454750031233,
      "throughput_images_per_sec": 0.17384808268923657,
      "image_height": 1024,
      "image_width": 1024
    },
    {
      "gpu_model": "H100",
      "num_gpus": 4,
      "batch_size": 2,
      "parallelization": {
        "ulysses_degree": 1,
        "ring_degree": 4
      },
      "batch_latency_s": 6.804342806339264,
      "avg_power_watts": 1921.9375216985584,
      "inference_steps": 50,
      "energy_per_image_joules": 6538.76087500155,
      "throughput_images_per_sec": 0.29392992929996126,
      "image_height": 1024,
      "image_width": 1024
    },
    {
      "gpu_model": "H100",
      "num_gpus": 8,
      "batch_size": 2,
      "parallelization": {
        "ulysses_degree": 1,
        "ring_degree": 8
      },
      "batch_latency_s": 7.744294762611389,
      "avg_power_watts": 2428.958197826567,
      "inference_steps": 50,
      "energy_per_image_joules": 9405.28412501514,
      "throughput_images_per_sec": 0.25825463277247424,
      "image_height": 1024,
      "image_width": 1024
    },
    {
      "gpu_model": "H100",
      "num_gpus": 2,
      "batch_size": 2,
      "parallelization": {
        "ulysses_degree": 2,
        "ring_degree": 1
      },
      "batch_latency_s": 11.635992884635925,
      "avg_power_watts": 956.1380245205545,
      "inference_steps": 50,
      "energy_per_image_joules": 5562.807625025511,
      "throughput_images_per_sec": 0.17188047636577575,
      "image_height": 1024,
      "image_width": 1024
    },
    {
      "gpu_model": "H100",
      "num_gpus": 4,
      "batch_size": 2,
      "parallelization": {
        "ulysses_degree": 2,
        "ring_degree": 2
      },
      "batch_latency_s": 6.7383270263671875,
      "avg_power_watts": 1860.8027928798958,
      "inference_steps": 50,
      "energy_per_image_joules": 6269.348875001073,
      "throughput_images_per_sec": 0.29680957783348394,
      "image_height": 1024,
      "image_width": 1024
    },
    {
      "gpu_model": "H100",
      "num_gpus": 8,
      "batch_size": 2,
      "parallelization": {
        "ulysses_degree": 2,
        "ring_degree": 4
      },
      "batch_latency_s": 6.463486731052399,
      "avg_power_watts": 2556.6268544508393,
      "inference_steps": 50,
      "energy_per_image_joules": 8262.361874997616,
      "throughput_images_per_sec": 0.3094305106857326,
      "image_height": 1024,
      "image_width": 1024
    },
    {
      "gpu_model": "H100",
      "num_gpus": 4,
      "batch_size": 2,
      "parallelization": {
        "ulysses_degree": 4,
        "ring_degree": 1
      },
      "batch_latency_s": 6.025704920291901,
      "avg_power_watts": 1986.914420533864,
      "inference_steps": 50,
      "energy_per_image_joules": 5986.280000004917,
      "throughput_images_per_sec": 0.33191137409747484,
      "image_height": 1024,
      "image_width": 1024
    },
    {
      "gpu_model": "H100",
      "num_gpus": 8,
      "batch_size": 2,
      "parallelization": {
        "ulysses_degree": 4,
        "ring_degree": 2
      },
      "batch_latency_s": 5.868672430515289,
      "avg_power_watts": 2598.9265341625837,
      "inference_steps": 50,
      "energy_per_image_joules": 7626.124249987304,
      "throughput_images_per_sec": 0.34079257680163166,
      "image_height": 1024,
      "image_width": 1024
    },
    {
      "gpu_model": "H100",
      "num_gpus": 8,
      "batch_size": 2,
      "parallelization": {
        "ulysses_degree": 8,
        "ring_degree": 1
      },
      "batch_latency_s": 5.303286135196686,
      "avg_power_watts": 2704.180556054919,
      "inference_steps": 50,
      "energy_per_image_joules": 7170.521624997258,
      "throughput_images_per_sec": 0.37712466365457104,
      "image_height": 1024,
      "image_width": 1024
    },
    {
      "gpu_model": "H100",
      "num_gpus": 2,
      "batch_size": 4,
      "parallelization": {
        "ulysses_degree": 1,
        "ring_degree": 2
      },
      "batch_latency_s": 21.037969172000885,
      "avg_power_watts": 1050.8119661772298,
      "inference_steps": 50,
      "energy_per_image_joules": 5526.73743750155,
      "throughput_images_per_sec": 0.19013242044881118,
      "image_height": 1024,
      "image_width": 1024
    },
    {
      "gpu_model": "H100",
      "num_gpus": 4,
      "batch_size": 4,
      "parallelization": {
        "ulysses_degree": 1,
        "ring_degree": 4
      },
      "batch_latency_s": 12.07226186990738,
      "avg_power_watts": 2180.2821031913145,
      "inference_steps": 50,
      "energy_per_image_joules": 6580.234124999493,
      "throughput_images_per_sec": 0.33133807426517403,
      "image_height": 1024,
      "image_width": 1024
    },
    {
      "gpu_model": "H100",
      "num_gpus": 8,
      "batch_size": 4,
      "parallelization": {
        "ulysses_degree": 1,
        "ring_degree": 8
      },
      "batch_latency_s": 10.378994643688202,
      "avg_power_watts": 3185.754582705249,
      "inference_steps": 50,
      "energy_per_image_joules": 8266.23243750073,
      "throughput_images_per_sec": 0.3853937820877986,
      "image_height": 1024,
      "image_width": 1024
    },
    {
      "gpu_model": "H100",
      "num_gpus": 2,
      "batch_size": 4,
      "parallelization": {
        "ulysses_degree": 2,
        "ring_degree": 1
      },
      "batch_latency_s": 21.069495379924774,
      "avg_power_watts": 1047.2496541581847,
      "inference_steps": 50,
      "energy_per_image_joules": 5516.255437478423,
      "throughput_images_per_sec": 0.18984792601208855,
      "image_height": 1024,
      "image_width": 1024
    },
    {
      "gpu_model": "H100",
      "num_gpus": 4,
      "batch_size": 4,
      "parallelization": {
        "ulysses_degree": 2,
        "ring_degree": 2
      },
      "batch_latency_s": 11.08732146024704,
      "avg_power_watts": 2273.3828761414566,
      "inference_steps": 50,
      "energy_per_image_joules": 6301.431687500328,
      "throughput_images_per_sec": 0.36077243853186475,
      "image_height": 1024,
      "image_width": 1024
    },
    {
      "gpu_model": "H100",
      "num_gpus": 8,
      "batch_size": 4,
      "parallelization": {
        "ulysses_degree": 2,
        "ring_degree": 4
      },
      "batch_latency_s": 7.755859613418579,
      "avg_power_watts": 3595.031549019998,
      "inference_steps": 50,
      "energy_per_image_joules": 6970.640000002459,
      "throughput_images_per_sec": 0.5157390926828426,
      "image_height": 1024,
      "image_width": 1024
    },
    {
      "gpu_model": "H100",
      "num_gpus": 4,
      "batch_size": 4,
      "parallelization": {
        "ulysses_degree": 4,
        "ring_degree": 1
      },
      "batch_latency_s": 10.702836334705353,
      "avg_power_watts": 2266.4088743783636,
      "inference_steps": 50,
      "energy_per_image_joules": 6064.250812498853,
      "throughput_images_per_sec": 0.3737327073786483,
      "image_height": 1024,
      "image_width": 1024
    },
    {
      "gpu_model": "H100",
      "num_gpus": 8,
      "batch_size": 4,
      "parallelization": {
        "ulysses_degree": 4,
        "ring_degree": 2
      },
      "batch_latency_s": 6.662841320037842,
      "avg_power_watts": 3872.031804573239,
      "inference_steps": 50,
      "energy_per_image_joules": 6449.683375002816,
      "throughput_images_per_sec": 0.6003444788592507,
      "image_height": 1024,
      "image_width": 1024
    },
    {
      "gpu_model": "H100",
      "num_gpus": 8,
      "batch_size": 4,
      "parallelization": {
        "ulysses_degree": 8,
        "ring_degree": 1
      },
      "batch_latency_s": 6.33799684047699,
      "avg_power_watts": 3942.9321485948954,
      "inference_steps": 50,
      "energy_per_image_joules": 6247.572875002399,
      "throughput_images_per_sec": 0.6311142306752815,
      "image_height": 1024,
      "image_width": 1024
    },
    {
      "gpu_model": "H100",
      "num_gpus": 2,
      "batch_size": 8,
      "parallelization": {
        "ulysses_degree": 1,
        "ring_degree": 2
      },
      "batch_latency_s": 39.499984323978424,
      "avg_power_watts": 1118.6455135643785,
      "inference_steps": 50,
      "energy_per_image_joules": 5523.310031235218,
      "throughput_images_per_sec": 0.20253172594662547,
      "image_height": 1024,
      "image_width": 1024
    },
    {
      "gpu_model": "H100",
      "num_gpus": 4,
      "batch_size": 8,
      "parallelization": {
        "ulysses_degree": 1,
        "ring_degree": 4
      },
      "batch_latency_s": 22.623268127441406,
      "avg_power_watts": 2330.582465051892,
      "inference_steps": 50,
      "energy_per_image_joules": 6590.673999997787,
      "throughput_images_per_sec": 0.353618228583704,
      "image_height": 1024,
      "image_width": 1024
    },
    {
      "gpu_model": "H100",
      "num_gpus": 8,
      "batch_size": 8,
      "parallelization": {
        "ulysses_degree": 1,
        "ring_degree": 8
      },
      "batch_latency_s": 19.45967608690262,
      "avg_power_watts": 3448.1484789548103,
      "inference_steps": 50,
      "energy_per_image_joules": 8387.48156250082,
      "throughput_images_per_sec": 0.41110653457301993,
      "image_height": 1024,
      "image_width": 1024
    },
    {
      "gpu_model": "H100",
      "num_gpus": 2,
      "batch_size": 8,
      "parallelization": {
        "ulysses_degree": 2,
        "ring_degree": 1
      },
      "batch_latency_s": 39.96319890022278,
      "avg_power_watts": 1099.3044715864164,
      "inference_steps": 50,
      "energy_per_image_joules": 5491.465406239033,
      "throughput_images_per_sec": 0.2001841749448992,
      "image_height": 1024,
      "image_width": 1024
    },
    {
      "gpu_model": "H100",
      "num_gpus": 4,
      "batch_size": 8,
      "parallelization": {
        "ulysses_degree": 2,
        "ring_degree": 2
      },
      "batch_latency_s": 20.54485285282135,
      "avg_power_watts": 2434.309282148256,
      "inference_steps": 50,
      "energy_per_image_joules": 6251.565749999136,
      "throughput_images_per_sec": 0.3893919346762997,
      "image_height": 1024,
      "image_width": 1024
    },
    {
      "gpu_model": "H100",
      "num_gpus": 8,
      "batch_size": 8,
      "parallelization": {
        "ulysses_degree": 2,
        "ring_degree": 4
      },
      "batch_latency_s": 13.093134045600891,
      "avg_power_watts": 4258.369753628911,
      "inference_steps": 50,
      "energy_per_image_joules": 6969.425749999471,
      "throughput_images_per_sec": 0.6110072632066184,
      "image_height": 1024,
      "image_width": 1024
    },
    {
      "gpu_model": "H100",
      "num_gpus": 4,
      "batch_size": 8,
      "parallelization": {
        "ulysses_degree": 4,
        "ring_degree": 1
      },
      "batch_latency_s": 19.94378697872162,
      "avg_power_watts": 2414.313104194222,
      "inference_steps": 50,
      "energy_per_image_joules": 6018.818281248212,
      "throughput_images_per_sec": 0.40112742923574857,
      "image_height": 1024,
      "image_width": 1024
    },
    {
      "gpu_model": "H100",
      "num_gpus": 8,
      "batch_size": 8,
      "parallelization": {
        "ulysses_degree": 4,
        "ring_degree": 2
      },
      "batch_latency_s": 11.992805778980255,
      "avg_power_watts": 4385.308093804191,
      "inference_steps": 50,
      "energy_per_image_joules": 6574.018531247973,
      "throughput_images_per_sec": 0.6670665853708371,
      "image_height": 1024,
      "image_width": 1024
    },
    {
      "gpu_model": "H100",
      "num_gpus": 8,
      "batch_size": 8,
      "parallelization": {
        "ulysses_degree": 8,
        "ring_degree": 1
      },
      "batch_latency_s": 11.261250793933868,
      "avg_power_watts": 4509.945558386965,
      "inference_steps": 50,
      "energy_per_image_joules": 6348.453499997966,
      "throughput_images_per_sec": 0.7104006603164706,
      "image_height": 1024,
      "image_width": 1024
    },
    {
      "gpu_model": "H100",
      "num_gpus": 1,
      "batch_size": 1,
      "parallelization": {
        "ulysses_degree": 1,
        "ring_degree": 1
      },
      "batch_latency_s": 8.375400483608246,
      "avg_power_watts": 618.5890167446029,
      "inference_steps": 50,
      "energy_per_image_joules": 5180.930749997497,
      "throughput_images_per_sec": 0.11939727562367086,
      "image_height": 1024,
      "image_width": 1024
    },
    {
      "gpu_model": "H100",
      "num_gpus": 1,
      "batch_size": 16,
      "parallelization": {
        "ulysses_degree": 1,
        "ring_degree": 1
      },
      "batch_latency_s": 121.16823917627335,
      "avg_power_watts": 665.8663487105575,
      "inference_steps": 50,
      "energy_per_image_joules": 5042.615812499542,
      "throughput_images_per_sec": 0.1320478048436727,
      "image_height": 1024,
      "image_width": 1024
    },
    {
      "gpu_model": "H100",
      "num_gpus": 1,
      "batch_size": 2,
      "parallelization": {
        "ulysses_degree": 1,
        "ring_degree": 1
      },
      "batch_latency_s": 15.978029131889343,
      "avg_power_watts": 648.5534551524697,
      "inference_steps": 50,
      "energy_per_image_joules": 5181.303000006825,
      "throughput_images_per_sec": 0.12517188343388053,
      "image_height": 1024,
      "image_width": 1024
    },
    {
      "gpu_model": "H100",
      "num_gpus": 1,
      "batch_size": 4,
      "parallelization": {
        "ulysses_degree": 1,
        "ring_degree": 1
      },
      "batch_latency_s": 30.982811987400055,
      "avg_power_watts": 665.4473941354111,
      "inference_steps": 50,
      "energy_per_image_joules": 5154.357875000685,
      "throughput_images_per_sec": 0.12910383994928223,
      "image_height": 1024,
      "image_width": 1024
    },
    {
      "gpu_model": "H100",
      "num_gpus": 1,
      "batch_size": 8,
      "parallelization": {
        "ulysses_degree": 1,
        "ring_degree": 1
      },
      "batch_latency_s": 60.8335839509964,
      "avg_power_watts": 671.7311038738181,
      "inference_steps": 50,
      "energy_per_image_joules": 5107.976312500425,
      "throughput_images_per_sec": 0.13150630754295659,
      "image_height": 1024,
      "image_width": 1024
    },
    {
      "gpu_model": "B200",
      "num_gpus": 8,
      "batch_size": 1,
      "parallelization": {
        "ulysses_degree": 1,
        "ring_degree": 8
      },
      "batch_latency_s": 7.215669572353363,
      "avg_power_watts": 2498.77018608355,
      "inference_steps": 50,
      "energy_per_image_joules": 18030.300000026822,
      "throughput_images_per_sec": 0.13858727730985246,
      "image_height": 1024,
      "image_width": 1024
    },
    {
      "gpu_model": "B200",
      "num_gpus": 8,
      "batch_size": 1,
      "parallelization": {
        "ulysses_degree": 2,
        "ring_degree": 4
      },
      "batch_latency_s": 6.2421388030052185,
      "avg_power_watts": 2575.995825700338,
      "inference_steps": 50,
      "energy_per_image_joules": 16079.72349998355,
      "throughput_images_per_sec": 0.1602015000881684,
      "image_height": 1024,
      "image_width": 1024
    },
    {
      "gpu_model": "B200",
      "num_gpus": 8,
      "batch_size": 1,
      "parallelization": {
        "ulysses_degree": 4,
        "ring_degree": 2
      },
      "batch_latency_s": 5.3898367285728455,
      "avg_power_watts": 2622.0475613027183,
      "inference_steps": 50,
      "energy_per_image_joules": 14132.40824997425,
      "throughput_images_per_sec": 0.18553437708024714,
      "image_height": 1024,
      "image_width": 1024
    },
    {
      "gpu_model": "B200",
      "num_gpus": 8,
      "batch_size": 1,
      "parallelization": {
        "ulysses_degree": 8,
        "ring_degree": 1
      },
      "batch_latency_s": 4.892130076885223,
      "avg_power_watts": 2693.800101979471,
      "inference_steps": 50,
      "energy_per_image_joules": 13178.420500010252,
      "throughput_images_per_sec": 0.20440993683403677,
      "image_height": 1024,
      "image_width": 1024
    },
    {
      "gpu_model": "B200",
      "num_gpus": 8,
      "batch_size": 16,
      "parallelization": {
        "ulysses_degree": 1,
        "ring_degree": 8
      },
      "batch_latency_s": 31.29129660129547,
      "avg_power_watts": 4426.6463775831935,
      "inference_steps": 50,
      "energy_per_image_joules": 8657.219046875369,
      "throughput_images_per_sec": 0.5113242894299751,
      "image_height": 1024,
      "image_width": 1024
    },
    {
      "gpu_model": "B200",
      "num_gpus": 8,
      "batch_size": 16,
      "parallelization": {
        "ulysses_degree": 2,
        "ring_degree": 4
      },
      "batch_latency_s": 20.130587995052338,
      "avg_power_watts": 5390.642130108457,
      "inference_steps": 50,
      "energy_per_image_joules": 6782.299734374043,
      "throughput_images_per_sec": 0.7948103653968008,
      "image_height": 1024,
      "image_width": 1024
    },
    {
      "gpu_model": "B200",
      "num_gpus": 8,
      "batch_size": 16,
      "parallelization": {
        "ulysses_degree": 4,
        "ring_degree": 2
      },
      "batch_latency_s": 17.167803049087524,
      "avg_power_watts": 5738.575749517998,
      "inference_steps": 50,
      "energy_per_image_joules": 6157.421140624676,
      "throughput_images_per_sec": 0.9319771408287683,
      "image_height": 1024,
      "image_width": 1024
    },
    {
      "gpu_model": "B200",
      "num_gpus": 8,
      "batch_size": 16,
      "parallelization": {
        "ulysses_degree": 8,
        "ring_degree": 1
      },
      "batch_latency_s": 16.32737499475479,
      "avg_power_watts": 5801.716873071438,
      "inference_steps": 50,
      "energy_per_image_joules": 5920.425437502097,
      "throughput_images_per_sec": 0.9799493185610081,
      "image_height": 1024,
      "image_width": 1024
    },
    {
      "gpu_model": "B200",
      "num_gpus": 8,
      "batch_size": 2,
      "parallelization": {
        "ulysses_degree": 1,
        "ring_degree": 8
      },
      "batch_latency_s": 7.299150764942169,
      "avg_power_watts": 3011.7752678307443,
      "inference_steps": 50,
      "energy_per_image_joules": 10991.700875010341,
      "throughput_images_per_sec": 0.27400447865880545,
      "image_height": 1024,
      "image_width": 1024
    },
    {
      "gpu_model": "B200",
      "num_gpus": 8,
      "batch_size": 2,
      "parallelization": {
        "ulysses_degree": 2,
        "ring_degree": 4
      },
      "batch_latency_s": 6.691580951213837,
      "avg_power_watts": 3024.1567198449197,
      "inference_steps": 50,
      "energy_per_image_joules": 10118.194749999791,
      "throughput_images_per_sec": 0.2988830314661597,
      "image_height": 1024,
      "image_width": 1024
    },
    {
      "gpu_model": "B200",
      "num_gpus": 8,
      "batch_size": 2,
      "parallelization": {
        "ulysses_degree": 4,
        "ring_degree": 2
      },
      "batch_latency_s": 5.800429284572601,
      "avg_power_watts": 3113.8898284725833,
      "inference_steps": 50,
      "energy_per_image_joules": 9030.948875002563,
      "throughput_images_per_sec": 0.34480206582629996,
      "image_height": 1024,
      "image_width": 1024
    },
    {
      "gpu_model": "B200",
      "num_gpus": 8,
      "batch_size": 2,
      "parallelization": {
        "ulysses_degree": 8,
        "ring_degree": 1
      },
      "batch_latency_s": 4.978055357933044,
      "avg_power_watts": 3261.2909223961665,
      "inference_steps": 50,
      "energy_per_image_joules": 8117.443375006318,
      "throughput_images_per_sec": 0.40176331040851,
      "image_height": 1024,
      "image_width": 1024
    },
    {
      "gpu_model": "B200",
      "num_gpus": 8,
      "batch_size": 32,
      "parallelization": {
        "ulysses_degree": 1,
        "ring_degree": 8
      },
      "batch_latency_s": 46.26564425230026,
      "avg_power_watts": 5388.784140568781,
      "inference_steps": 50,
      "energy_per_image_joules": 7791.1115624997765,
      "throughput_images_per_sec": 0.6916579357567036,
      "image_height": 1024,
      "image_width": 1024
    },
    {
      "gpu_model": "B200",
      "num_gpus": 8,
      "batch_size": 32,
      "parallelization": {
        "ulysses_degree": 2,
        "ring_degree": 4
      },
      "batch_latency_s": 38.52486699819565,
      "avg_power_watts": 5705.71135937464,
      "inference_steps": 50,
      "energy_per_image_joules": 6869.117851562565,
      "throughput_images_per_sec": 0.8306323290226739,
      "image_height": 1024,
      "image_width": 1024
    },
    {
      "gpu_model": "B200",
      "num_gpus": 8,
      "batch_size": 32,
      "parallelization": {
        "ulysses_degree": 4,
        "ring_degree": 2
      },
      "batch_latency_s": 32.82585322856903,
      "avg_power_watts": 6107.291746662449,
      "inference_steps": 50,
      "energy_per_image_joules": 6264.908203124767,
      "throughput_images_per_sec": 0.9748413781412306,
      "image_height": 1024,
      "image_width": 1024
    },
    {
      "gpu_model": "B200",
      "num_gpus": 8,
      "batch_size": 32,
      "parallelization": {
        "ulysses_degree": 8,
        "ring_degree": 1
      },
      "batch_latency_s": 31.337716341018677,
      "avg_power_watts": 6146.140457525062,
      "inference_steps": 50,
      "energy_per_image_joules": 6018.937695311848,
      "throughput_images_per_sec": 1.0211337562627192,
      "image_height": 1024,
      "image_width": 1024
    },
    {
      "gpu_model": "B200",
      "num_gpus": 8,
      "batch_size": 4,
      "parallelization": {
        "ulysses_degree": 1,
        "ring_degree": 8
      },
      "batch_latency_s": 9.553734958171844,
      "avg_power_watts": 3668.330360163758,
      "inference_steps": 50,
      "energy_per_image_joules": 8761.564000004902,
      "throughput_images_per_sec": 0.4186844221147852,
      "image_height": 1024,
      "image_width": 1024
    },
    {
      "gpu_model": "B200",
      "num_gpus": 8,
      "batch_size": 4,
      "parallelization": {
        "ulysses_degree": 2,
        "ring_degree": 4
      },
      "batch_latency_s": 7.044357895851135,
      "avg_power_watts": 4030.1699487359256,
      "inference_steps": 50,
      "energy_per_image_joules": 7097.48987499997,
      "throughput_images_per_sec": 0.5678303202561373,
      "image_height": 1024,
      "image_width": 1024
    },
    {
      "gpu_model": "B200",
      "num_gpus": 8,
      "batch_size": 4,
      "parallelization": {
        "ulysses_degree": 4,
        "ring_degree": 2
      },
      "batch_latency_s": 5.983519554138184,
      "avg_power_watts": 4261.349155677091,
      "inference_steps": 50,
      "energy_per_image_joules": 6374.466500001028,
      "throughput_images_per_sec": 0.6685028708953766,
      "image_height": 1024,
      "image_width": 1024
    },
    {
      "gpu_model": "B200",
      "num_gpus": 8,
      "batch_size": 4,
      "parallelization": {
        "ulysses_degree": 8,
        "ring_degree": 1
      },
      "batch_latency_s": 5.777193605899811,
      "avg_power_watts": 4254.0275480660475,
      "inference_steps": 50,
      "energy_per_image_joules": 6144.085187502205,
      "throughput_images_per_sec": 0.6923776963117703,
      "image_height": 1024,
      "image_width": 1024
    },
    {
      "gpu_model": "B200",
      "num_gpus": 8,
      "batch_size": 8,
      "parallelization": {
        "ulysses_degree": 1,
        "ring_degree": 8
      },
      "batch_latency_s": 16.09741872549057,
      "avg_power_watts": 4141.422602398973,
      "inference_steps": 50,
      "energy_per_image_joules": 8333.27671875339,
      "throughput_images_per_sec": 0.4969740886053891,
      "image_height": 1024,
      "image_width": 1024
    },
    {
      "gpu_model": "B200",
      "num_gpus": 8,
      "batch_size": 8,
      "parallelization": {
        "ulysses_degree": 2,
        "ring_degree": 4
      },
      "batch_latency_s": 10.840566515922546,
      "avg_power_watts": 4880.420079734668,
      "inference_steps": 50,
      "energy_per_image_joules": 6613.314812500961,
      "throughput_images_per_sec": 0.7379688126307474,
      "image_height": 1024,
      "image_width": 1024
    },
    {
      "gpu_model": "B200",
      "num_gpus": 8,
      "batch_size": 8,
      "parallelization": {
        "ulysses_degree": 4,
        "ring_degree": 2
      },
      "batch_latency_s": 9.253413021564484,
      "avg_power_watts": 5162.094990105381,
      "inference_steps": 50,
      "energy_per_image_joules": 5970.87462499924,
      "throughput_images_per_sec": 0.864545868789874,
      "image_height": 1024,
      "image_width": 1024
    },
    {
      "gpu_model": "B200",
      "num_gpus": 8,
      "batch_size": 8,
      "parallelization": {
        "ulysses_degree": 8,
        "ring_degree": 1
      },
      "batch_latency_s": 8.883395314216614,
      "avg_power_watts": 5169.6796242421815,
      "inference_steps": 50,
      "energy_per_image_joules": 5740.538468749262,
      "throughput_images_per_sec": 0.9005565684099563,
      "image_height": 1024,
      "image_width": 1024
    },
    {
      "gpu_model": "B200",
      "num_gpus": 4,
      "batch_size": 1,
      "parallelization": {
        "ulysses_degree": 1,
        "ring_degree": 4
      },
      "batch_latency_s": 5.5896759033203125,
      "avg_power_watts": 1581.5939784181887,
      "inference_steps": 50,
      "energy_per_image_joules": 8840.597750000656,
      "throughput_images_per_sec": 0.17890124889101208,
      "image_height": 1024,
      "image_width": 1024
    },
    {
      "gpu_model": "B200",
      "num_gpus": 4,
      "batch_size": 1,
      "parallelization": {
        "ulysses_degree": 2,
        "ring_degree": 2
      },
      "batch_latency_s": 5.595264792442322,
      "avg_power_watts": 1578.8597283082543,
      "inference_steps": 50,
      "energy_per_image_joules": 8834.138250008225,
      "throughput_images_per_sec": 0.17872255149581617,
      "image_height": 1024,
      "image_width": 1024
    },
    {
      "gpu_model": "B200",
      "num_gpus": 4,
      "batch_size": 1,
      "parallelization": {
        "ulysses_degree": 4,
        "ring_degree": 1
      },
      "batch_latency_s": 4.694942116737366,
      "avg_power_watts": 1669.0633356385401,
      "inference_steps": 50,
      "energy_per_image_joules": 7836.155749991536,
      "throughput_images_per_sec": 0.2129951712152152,
      "image_height": 1024,
      "image_width": 1024
    },
    {
      "gpu_model": "B200",
      "num_gpus": 4,
      "batch_size": 16,
      "parallelization": {
        "ulysses_degree": 1,
        "ring_degree": 4
      },
      "batch_latency_s": 34.27704209089279,
      "avg_power_watts": 3008.1659241933226,
      "inference_steps": 50,
      "energy_per_image_joules": 6444.439374997746,
      "throughput_images_per_sec": 0.46678473473798093,
      "image_height": 1024,
      "image_width": 1024
    },
    {
      "gpu_model": "B200",
      "num_gpus": 4,
      "batch_size": 16,
      "parallelization": {
        "ulysses_degree": 2,
        "ring_degree": 2
      },
      "batch_latency_s": 31.000922560691833,
      "avg_power_watts": 3132.6920855298163,
      "inference_steps": 50,
      "energy_per_image_joules": 6069.771546875127,
      "throughput_images_per_sec": 0.5161136727036466,
      "image_height": 1024,
      "image_width": 1024
    },
    {
      "gpu_model": "B200",
      "num_gpus": 4,
      "batch_size": 16,
      "parallelization": {
        "ulysses_degree": 4,
        "ring_degree": 1
      },
      "batch_latency_s": 29.51697999238968,
      "avg_power_watts": 3169.8509391579196,
      "inference_steps": 50,
      "energy_per_image_joules": 5847.776671873871,
      "throughput_images_per_sec": 0.5420608749311501,
      "image_height": 1024,
      "image_width": 1024
    },
    {
      "gpu_model": "B200",
      "num_gpus": 4,
      "batch_size": 2,
      "parallelization": {
        "ulysses_degree": 1,
        "ring_degree": 4
      },
      "batch_latency_s": 6.4156299233436584,
      "avg_power_watts": 2080.133542529972,
      "inference_steps": 50,
      "energy_per_image_joules": 6672.68350000307,
      "throughput_images_per_sec": 0.31173867942770184,
      "image_height": 1024,
      "image_width": 1024
    },
    {
      "gpu_model": "B200",
      "num_gpus": 4,
      "batch_size": 2,
      "parallelization": {
        "ulysses_degree": 2,
        "ring_degree": 2
      },
      "batch_latency_s": 5.840083062648773,
      "avg_power_watts": 2135.8232607619684,
      "inference_steps": 50,
      "energy_per_image_joules": 6236.692624993622,
      "throughput_images_per_sec": 0.3424608825842451,
      "image_height": 1024,
      "image_width": 1024
    },
    {
      "gpu_model": "B200",
      "num_gpus": 4,
      "batch_size": 2,
      "parallelization": {
        "ulysses_degree": 4,
        "ring_degree": 1
      },
      "batch_latency_s": 5.575142800807953,
      "avg_power_watts": 2146.1117100428582,
      "inference_steps": 50,
      "energy_per_image_joules": 5982.439624987543,
      "throughput_images_per_sec": 0.35873520579780643,
      "image_height": 1024,
      "image_width": 1024
    },
    {
      "gpu_model": "B200",
      "num_gpus": 4,
      "batch_size": 4,
      "parallelization": {
        "ulysses_degree": 1,
        "ring_degree": 4
      },
      "batch_latency_s": 9.575963914394379,
      "avg_power_watts": 2585.6752616637273,
      "inference_steps": 50,
      "energy_per_image_joules": 6190.0832500085235,
      "throughput_images_per_sec": 0.4177125181087293,
      "image_height": 1024,
      "image_width": 1024
    },
    {
      "gpu_model": "B200",
      "num_gpus": 4,
      "batch_size": 4,
      "parallelization": {
        "ulysses_degree": 2,
        "ring_degree": 2
      },
      "batch_latency_s": 8.82723331451416,
      "avg_power_watts": 2657.65134602698,
      "inference_steps": 50,
      "energy_per_image_joules": 5864.927125003189,
      "throughput_images_per_sec": 0.45314311489003106,
      "image_height": 1024,
      "image_width": 1024
    },
    {
      "gpu_model": "B200",
      "num_gpus": 4,
      "batch_size": 4,
      "parallelization": {
        "ulysses_degree": 4,
        "ring_degree": 1
      },
      "batch_latency_s": 8.361985683441162,
      "avg_power_watts": 2675.72229217353,
      "inference_steps": 50,
      "energy_per_image_joules": 5593.587875004858,
      "throughput_images_per_sec": 0.47835527964619784,
      "image_height": 1024,
      "image_width": 1024
    },
    {
      "gpu_model": "B200",
      "num_gpus": 4,
      "batch_size": 8,
      "parallelization": {
        "ulysses_degree": 1,
        "ring_degree": 4
      },
      "batch_latency_s": 18.43435424566269,
      "avg_power_watts": 2779.6865605996304,
      "inference_steps": 50,
      "energy_per_image_joules": 6405.215843750164,
      "throughput_images_per_sec": 0.4339723482249058,
      "image_height": 1024,
      "image_width": 1024
    },
    {
      "gpu_model": "B200",
      "num_gpus": 4,
      "batch_size": 8,
      "parallelization": {
        "ulysses_degree": 2,
        "ring_degree": 2
      },
      "batch_latency_s": 16.2739816904068,
      "avg_power_watts": 2927.073466481356,
      "inference_steps": 50,
      "energy_per_image_joules": 5954.392499999143,
      "throughput_images_per_sec": 0.4915822170745004,
      "image_height": 1024,
      "image_width": 1024
    },
    {
      "gpu_model": "B200",
      "num_gpus": 4,
      "batch_size": 8,
      "parallelization": {
        "ulysses_degree": 4,
        "ring_degree": 1
      },
      "batch_latency_s": 15.515216708183289,
      "avg_power_watts": 2957.1678960684467,
      "inference_steps": 50,
      "energy_per_image_joules": 5735.137593748048,
      "throughput_images_per_sec": 0.5156228334071873,
      "image_height": 1024,
      "image_width": 1024
    },
    {
      "gpu_model": "B200",
      "num_gpus": 2,
      "batch_size": 1,
      "parallelization": {
        "ulysses_degree": 1,
        "ring_degree": 2
      },
      "batch_latency_s": 5.680253088474274,
      "avg_power_watts": 1069.0864307304792,
      "inference_steps": 50,
      "energy_per_image_joules": 6072.681500002742,
      "throughput_images_per_sec": 0.17604849368931935,
      "image_height": 1024,
      "image_width": 1024
    },
    {
      "gpu_model": "B200",
      "num_gpus": 2,
      "batch_size": 1,
      "parallelization": {
        "ulysses_degree": 2,
        "ring_degree": 1
      },
      "batch_latency_s": 5.643208026885986,
      "avg_power_watts": 1067.9655917779464,
      "inference_steps": 50,
      "energy_per_image_joules": 6026.75199995935,
      "throughput_images_per_sec": 0.17720417096723903,
      "image_height": 1024,
      "image_width": 1024
    },
    {
      "gpu_model": "B200",
      "num_gpus": 2,
      "batch_size": 16,
      "parallelization": {
        "ulysses_degree": 1,
        "ring_degree": 2
      },
      "batch_latency_s": 54.16801738739014,
      "avg_power_watts": 1666.4709103972646,
      "inference_steps": 50,
      "energy_per_image_joules": 5641.839078123681,
      "throughput_images_per_sec": 0.29537724974450824,
      "image_height": 1024,
      "image_width": 1024
    },
    {
      "gpu_model": "B200",
      "num_gpus": 2,
      "batch_size": 16,
      "parallelization": {
        "ulysses_degree": 2,
        "ring_degree": 1
      },
      "batch_latency_s": 55.52383440732956,
      "avg_power_watts": 1634.9335869718882,
      "inference_steps": 50,
      "energy_per_image_joules": 5673.611359375529,
      "throughput_images_per_sec": 0.28816453637949546,
      "image_height": 1024,
      "image_width": 1024
    },
    {
      "gpu_model": "B200",
      "num_gpus": 2,
      "batch_size": 2,
      "parallelization": {
        "ulysses_degree": 1,
        "ring_degree": 2
      },
      "batch_latency_s": 8.222081243991852,
      "avg_power_watts": 1347.422133305348,
      "inference_steps": 50,
      "energy_per_image_joules": 5539.307124994695,
      "throughput_images_per_sec": 0.24324741396364413,
      "image_height": 1024,
      "image_width": 1024
    },
    {
      "gpu_model": "B200",
      "num_gpus": 2,
      "batch_size": 2,
      "parallelization": {
        "ulysses_degree": 2,
        "ring_degree": 1
      },
      "batch_latency_s": 8.350828409194946,
      "avg_power_watts": 1315.0222602958986,
      "inference_steps": 50,
      "energy_per_image_joules": 5490.762625001371,
      "throughput_images_per_sec": 0.23949719740353378,
      "image_height": 1024,
      "image_width": 1024
    },
    {
      "gpu_model": "B200",
      "num_gpus": 2,
      "batch_size": 4,
      "parallelization": {
        "ulysses_degree": 1,
        "ring_degree": 2
      },
      "batch_latency_s": 14.97512286901474,
      "avg_power_watts": 1509.1839444436969,
      "inference_steps": 50,
      "energy_per_image_joules": 5650.053749997169,
      "throughput_images_per_sec": 0.26710966146905296,
      "image_height": 1024,
      "image_width": 1024
    },
    {
      "gpu_model": "B200",
      "num_gpus": 2,
      "batch_size": 4,
      "parallelization": {
        "ulysses_degree": 2,
        "ring_degree": 1
      },
      "batch_latency_s": 15.198670864105225,
      "avg_power_watts": 1490.5172269693237,
      "inference_steps": 50,
      "energy_per_image_joules": 5663.470187496394,
      "throughput_images_per_sec": 0.26318090810472244,
      "image_height": 1024,
      "image_width": 1024
    },
    {
      "gpu_model": "B200",
      "num_gpus": 2,
      "batch_size": 8,
      "parallelization": {
        "ulysses_degree": 1,
        "ring_degree": 2
      },
      "batch_latency_s": 28.127986013889313,
      "avg_power_watts": 1627.3379020947748,
      "inference_steps": 50,
      "energy_per_image_joules": 5721.717218749225,
      "throughput_images_per_sec": 0.2844142483592562,
      "image_height": 1024,
      "image_width": 1024
    },
    {
      "gpu_model": "B200",
      "num_gpus": 2,
      "batch_size": 8,
      "parallelization": {
        "ulysses_degree": 2,
        "ring_degree": 1
      },
      "batch_latency_s": 28.851106226444244,
      "avg_power_watts": 1571.951397427518,
      "inference_steps": 50,
      "energy_per_image_joules": 5669.067093748599,
      "throughput_images_per_sec": 0.27728572822165787,
      "image_height": 1024,
      "image_width": 1024
    },
    {
      "gpu_model": "B200",
      "num_gpus": 1,
      "batch_size": 1,
      "parallelization": {
        "ulysses_degree": 1,
        "ring_degree": 1
      },
      "batch_latency_s": 6.278908848762512,
      "avg_power_watts": 702.3470727490993,
      "inference_steps": 50,
      "energy_per_image_joules": 4409.973249986768,
      "throughput_images_per_sec": 0.15926334082666074,
      "image_height": 1024,
      "image_width": 1024
    },
    {
      "gpu_model": "B200",
      "num_gpus": 1,
      "batch_size": 16,
      "parallelization": {
        "ulysses_degree": 1,
        "ring_degree": 1
      },
      "batch_latency_s": 91.03747928142548,
      "avg_power_watts": 832.6831882688259,
      "inference_steps": 50,
      "energy_per_image_joules": 4737.836156250909,
      "throughput_images_per_sec": 0.17575179065029875,
      "image_height": 1024,
      "image_width": 1024
    },
    {
      "gpu_model": "B200",
      "num_gpus": 1,
      "batch_size": 2,
      "parallelization": {
        "ulysses_degree": 1,
        "ring_degree": 1
      },
      "batch_latency_s": 12.193998456001282,
      "avg_power_watts": 776.2767917486475,
      "inference_steps": 50,
      "energy_per_image_joules": 4732.959000006318,
      "throughput_images_per_sec": 0.16401511015574216,
      "image_height": 1024,
      "image_width": 1024
    },
    {
      "gpu_model": "B200",
      "num_gpus": 1,
      "batch_size": 4,
      "parallelization": {
        "ulysses_degree": 1,
        "ring_degree": 1
      },
      "batch_latency_s": 23.633387446403503,
      "avg_power_watts": 770.5392653214553,
      "inference_steps": 50,
      "energy_per_image_joules": 4552.613250002265,
      "throughput_images_per_sec": 0.16925208072991307,
      "image_height": 1024,
      "image_width": 1024
    },
    {
      "gpu_model": "B200",
      "num_gpus": 1,
      "batch_size": 8,
      "parallelization": {
        "ulysses_degree": 1,
        "ring_degree": 1
      },
      "batch_latency_s": 46.234221041202545,
      "avg_power_watts": 815.417247246229,
      "inference_steps": 50,
      "energy_per_image_joules": 4712.522656248882,
      "throughput_images_per_sec": 0.17303200572733,
      "image_height": 1024,
      "image_width": 1024
    }
  ]
}